MANIFEST.in
README.md
setup.py
gitset/__init__.py
gitset/__version__.py
gitset/cli.py
gitset/exceptions.py
gitset/help.py
gitset/models.py
gitset/status_codes.py
gitset/utils.py
gitset.egg-info/PKG-INFO
gitset.egg-info/SOURCES.txt
gitset.egg-info/dependency_links.txt
gitset.egg-info/entry_points.txt
gitset.egg-info/not-zip-safe
gitset.egg-info/requires.txt
gitset.egg-info/top_level.txt